PyCardDeck/__init__.py
PyCardDeck/card.py
PyCardDeck/deck.py
PyCardDeck/errors.py
PyCardDeck/hand.py
CardDeckPy-2.1.0.dist-info/LICENSE
CardDeckPy-2.1.0.dist-info/METADATA
CardDeckPy-2.1.0.dist-info/WHEEL
CardDeckPy-2.1.0.dist-info/top_level.txt
CardDeckPy-2.1.0.dist-info/RECORD
