Metadata-Version: 2.1
Name: CardDeckPy
Version: 2.1.0
Summary: A library for working with cards, decks, and hands in python
Home-page: https://replit.com/@IsraelW/Card-Deck-Python
Author: Israel Waldner
Author-email: imky171@gmail.com
License: UNKNOWN
Platform: UNKNOWN
Classifier: Programming Language :: Python :: 3
Classifier: License :: OSI Approved :: MIT License
Classifier: Operating System :: OS Independent
Requires-Python: >=3.0
